pystackalytics/__init__.py
pystackalytics/pystackalytics.py
pystackalytics-0.1.3.dist-info/DESCRIPTION.rst
pystackalytics-0.1.3.dist-info/METADATA
pystackalytics-0.1.3.dist-info/RECORD
pystackalytics-0.1.3.dist-info/WHEEL
pystackalytics-0.1.3.dist-info/metadata.json
pystackalytics-0.1.3.dist-info/top_level.txt
