Metadata-Version: 2.0
Name: pystackalytics
Version: 0.1.3
Summary: Python wrapper for Mirantis Stackalytics API.
Home-page: https://github.com/vu3jej/pystackalytics
Author: Jithesh E J
Author-email: mail@jithesh.net
License: MIT
Keywords: pystackalytics
Platform: UNKNOWN
Classifier: Development Status :: 2 - Pre-Alpha
Classifier: Intended Audience :: Developers
Classifier: License :: OSI Approved :: ISC License (ISCL)
Classifier: Natural Language :: English
Classifier: Programming Language :: Python :: 2
Classifier: Programming Language :: Python :: 2.6
Classifier: Programming Language :: Python :: 2.7
Classifier: Programming Language :: Python :: 3
Classifier: Programming Language :: Python :: 3.3
Classifier: Programming Language :: Python :: 3.4
Requires-Dist: requests
